downloadImages/__init__.py
downloadImages/crawler/__init__.py
downloadImages/crawler/crawler.py
downloadImages/crawler/defaultConfig.py
downloadImages/downloader/__init__.py
downloadImages/downloader/customExceptions.py
downloadImages/downloader/generic.py
downloadImages/downloader/wallhavenImage.py
downloadimages-0.0.1.dist-info/METADATA
downloadimages-0.0.1.dist-info/WHEEL
downloadimages-0.0.1.dist-info/top_level.txt
downloadimages-0.0.1.dist-info/RECORD
