Metadata-Version: 2.1
Name: downloadimages
Version: 0.0.1
Summary: Get image url from a few website
Home-page: https://github.com/diepthuyhan/downloadImages
Author: diepthuyhan
Author-email: 
License: UNKNOWN
Platform: UNKNOWN
Classifier: Programming Language :: Python :: 3
Classifier: License :: OSI Approved :: MIT License
Classifier: Operating System :: OS Independent
Requires-Python: >=3.6
